Metadata-Version: 2.1
Name: colordev
Version: 0.2.0
Summary: Terminal Text package,     which allows you to output text with different stylized colors in the terminal
Home-page: UNKNOWN
Author: Oleg Bazaka
Author-email: bazaka.developer@gmail.com
License: UNKNOWN
Platform: UNKNOWN
